enbios/__init__.py
enbios/const.py
enbios/base/__init__.py
enbios/base/experiment.py
enbios/base/experiment_io.py
enbios/base/models.py
enbios/base/plot_experiment.py
enbios/base/pydantic_experiment_validation.py
enbios/base/result_select.py
enbios/base/scenario.py
enbios/base/tree_operations.py
enbios/base/unit_registry.py
enbios/base/validation.py
enbios/base/adapters_aggregators/__init__.py
enbios/base/adapters_aggregators/adapter.py
enbios/base/adapters_aggregators/aggregator.py
enbios/base/adapters_aggregators/loader.py
enbios/base/adapters_aggregators/node_module.py
enbios/base/adapters_aggregators/builtin/__init__.py
enbios/base/adapters_aggregators/builtin/assignment_adapter.py
enbios/base/adapters_aggregators/builtin/sum_aggregator.py
enbios/bw2/MultiLCA_util.py
enbios/bw2/__init__.py
enbios/bw2/brightway_experiment_adapter.py
enbios/bw2/bw_models.py
enbios/bw2/check_bw_acts_normal.py
enbios/bw2/import_ecoinvent.py
enbios/bw2/regionalization.py
enbios/bw2/resolve_lca_bioflows.py
enbios/bw2/util.py
enbios/dev/__init__.py
enbios/dev/create_experiment_schema.py
enbios/dev/docs_api_inject.py
enbios/generic/__init__.py
enbios/generic/enbios2_logging.py
enbios/generic/files.py
enbios/generic/mermaid2hierarchy.py
enbios/generic/output_merge.py
enbios/generic/unit_util.py
enbios/generic/util.py
enbios/generic/flatten_dict/__init__.py
enbios/generic/flatten_dict/flatten_dict.py
enbios/generic/flatten_dict/reducers.py
enbios/generic/flatten_dict/splitters.py
enbios/generic/tree/__init__.py
enbios/generic/tree/basic_tree.py
enbios-2.2.11.dist-info/LICENSE
enbios-2.2.11.dist-info/METADATA
enbios-2.2.11.dist-info/WHEEL
enbios-2.2.11.dist-info/top_level.txt
enbios-2.2.11.dist-info/RECORD
